deploydocus/__init__.py
deploydocus/__main__.py
deploydocus/appstate/__init__.py
deploydocus/appstate/binutils.py
deploydocus/appstate/helm3/__init__.py
deploydocus/appstate/helm3/helm.py
deploydocus/appstate/helm3/helm_shell.py
deploydocus/appstate/kustomize/__init__.py
deploydocus/appstate/kustomize/kustomize.py
deploydocus/appstate/sources/__init__.py
deploydocus/appstate/sources/git/__init__.py
deploydocus/appstate/sources/git/git.py
deploydocus/appstate/sources/pypi/__init__.py
deploydocus/cli/__init__.py
deploydocus/cli/main.py
deploydocus/installer.py
deploydocus/logging/__init__.py
deploydocus/logging/configure.py
deploydocus/package/__init__.py
deploydocus/package/errors.py
deploydocus/package/installer.py
deploydocus/package/pkg.py
deploydocus/package/settings.py
deploydocus/package/types.py
deploydocus/package/utils.py
deploydocus-0.0.1a1.dist-info/LICENSE.md
deploydocus-0.0.1a1.dist-info/METADATA
deploydocus-0.0.1a1.dist-info/WHEEL
deploydocus-0.0.1a1.dist-info/entry_points.txt
deploydocus-0.0.1a1.dist-info/RECORD
