Metadata-Version: 2.1
Name: deploydocus
Version: 0.0.1a1
Summary: A library and CLI to install/uninstall Kubernetes applications to clusters.
License: AGPL-3.0-or-later
Author: Partho Bhowmick
Author-email: partho.bhowmick@icloud.com
Requires-Python: >=3.12,<4.0
Classifier: Development Status :: 2 - Pre-Alpha
Classifier: Intended Audience :: Developers
Classifier: Intended Audience :: System Administrators
Classifier: License :: OSI Approved :: GNU Affero General Public License v3 or later (AGPLv3+)
Classifier: Programming Language :: Python :: 3
Classifier: Programming Language :: Python :: 3.12
Classifier: Programming Language :: Python :: 3.13
Classifier: Typing :: Typed
Requires-Dist: kubernetes (>=27,<31)
Requires-Dist: plumbum (>=1.8,<2.0)
Requires-Dist: pydantic (>=2.8,<3.0)
Requires-Dist: pydantic-settings (>=2.3,<3.0)
Requires-Dist: pyyaml[libyaml] (>=6.0.2,<7.0.0)
Requires-Dist: typer (>=0.13.0,<0.14.0)
Requires-Dist: types-pyyaml (>=6.0,<7.0)
